{
	"name": "7_explore_trip_data_green",
	"properties": {
		"folder": {
			"name": "nyc_taxi/Discovery"
		},
		"content": {
			"query": "SELECT\n    TOP 100 *\nFROM\n    OPENROWSET(\n        BULK 'raw/trip_data_green_csv/year=2020/month=01/',\n        DATA_SOURCE = 'nyc_taxi_data',\n        FORMAT = 'CSV',\n        HEADER_ROW = TRUE,\n        PARSER_VERSION = '2.0'\n) AS [result];\n\n-- Leer metadata\n\nSELECT\n    TOP 100\n    result.filename() AS file_name,\n    result.filepath() AS file_name,\n    result.*\nFROM\n    OPENROWSET(\n        BULK 'raw/trip_data_green_csv/year=2020/**',\n        DATA_SOURCE = 'nyc_taxi_data',\n        FORMAT = 'CSV',\n        HEADER_ROW = TRUE,\n        PARSER_VERSION = '2.0'\n) AS result;\n\n-- Leer Parquet\n\nSELECT\n    TOP 100 *\nFROM\n    OPENROWSET(\n        BULK 'raw/trip_data_green_parquet/year=2020/month=01/part-00000-tid-6133789922049958496-2e489315-890a-4453-ae93-a104be9a6f06-106-1-c000.snappy.parquet',\n        DATA_SOURCE = 'nyc_taxi_data',\n        FORMAT = 'PARQUET'\n    ) AS [result]\n\n-- Leer Delta\n\nSELECT\n    TOP 100 *\nFROM\n    OPENROWSET(\n        BULK 'raw/trip_data_green_delta',\n        DATA_SOURCE = 'nyc_taxi_data',\n        FORMAT = 'DELTA'\n    ) AS [result]",
			"metadata": {
				"language": "sql"
			},
			"currentConnection": {
				"databaseName": "nyc_taxi_discovery",
				"poolName": "Built-in"
			},
			"resultLimit": 5000
		},
		"type": "SqlQuery"
	}
}